agns/__init__.py
agns/agent.py
agns/agent_resolver.py
agns/client.py
agns/a2a/a2a_agent_caller.py
agns/a2a/a2a_http_server.py
agns/mcp/mcp_agent_caller.py
agns/mcp/mcp_client.py
agns/mcp/mcp_server.py
agns/model/agent_card.py
agns-0.1.4.dist-info/licenses/LICENSE
agns-0.1.4.dist-info/METADATA
agns-0.1.4.dist-info/WHEEL
agns-0.1.4.dist-info/top_level.txt
agns-0.1.4.dist-info/RECORD
