Metadata-Version: 2.4
Name: agns
Version: 0.1.4
Summary: AI Agent Name Service SDK
Author-email: Your Name <you@example.com>
License: MIT
Project-URL: Homepage, https://github.com/yourusername/aans-sdk
Project-URL: Repository, https://github.com/yourusername/aans-sdk
Requires-Python: >=3.8
License-File: LICENSE
Requires-Dist: requests>=2.31.0
Requires-Dist: pydantic>=2.5.3
Dynamic: license-file
